[
  {
    "secondaireSports": "Jogging",
    "favoriteSports": "Biking",
    "commentsFriends": [
      {
        "likes": 6,
        "comments": "Aute incididunt anim veniam est. Et in officia velit culpa. Nulla proident labore est duis anim. Est occaecat sit do est eu consectetur tempor voluptate aliqua laborum anim non. Dolore nulla laboris enim dolore est ea. Ea mollit fugiat laboris incididunt non qui tempor velit.",
        "picture": "http://placehold.it/32x32",
        "name": "Noemi Pitts",
        "id": 0
      }
    ],
    "longitude": "-123.305573",
    "latitude": "-4.226987",
    "registered": "Saturday, February 22, 2014 11:32 AM",
    "address": "320 Tapscott Avenue, Vaughn, Nevada, 6425",
    "houseAvailability": "2 nights minimum stay",
    "houseSpaceDescription": "Et in est fugiat aute magna in occaecat laborum ipsum fugiat sint. Id deserunt amet ea est deserunt dolor.",
    "housePrices": {
      "cancellation": "est",
      "securityDeposit": "$3,745.23",
      "monthlyDiscount": "300%",
      "cleaningFee": "$2,076.16",
      "weeklyDiscount": "200%",
      "extraBabyBed": "$1,290.21 do eu"
    },
    "houseAmenities": {
      "more": "Nulla nulla velit dolore nulla laborum minim ex.",
      "bbq": false,
      "essentials": false,
      "TV": true,
      "wifi": false,
      "kitchen": true
    },
    "houseSpace": {
      "houseRules": "Minim Lorem non non mollit cillum magna esse cillum ut occaecat quis fugiat proident deserunt. Dolore dolor dolor esse amet nostrud esse elit minim duis. Minim nulla ipsum veniam do culpa aliquip fugiat do sit officia sit officia. Elit occaecat aliquip aliqua enim deserunt magna sit consectetur laboris velit.",
      "checkOut": "11:00 AM",
      "checkIn": "2:00 PM",
      "propertyType": "culpa tempor",
      "beds": 1,
      "bedrooms": 4,
      "bathrooms": 5,
      "accommodates": 6
    },
    "houseListing": {
      "valueForMoney": "5 stars",
      "location": "5 stars",
      "cleanness": "5 stars",
      "price": "$1,302.45",
      "country": "Botswana",
      "state": "South Dakota",
      "description": "Eu est aliqua irure do amet voluptate excepteur non anim et consequat. Consectetur non id officia esse Lorem labore in minim minim adipisicing sit labore velit ea. Et nostrud enim incididunt est.",
      "title": "Aute pariatur sit ut ut pariatur irure nostrud consequat pariatur nostrud."
    },
    "name": {
      "last": "Bush",
      "first": "Virgie"
    },
    "picture": "http://placehold.it/1900x400",
    "isActive": true,
    "guid": "88b356f2-efb8-441c-b768-c88da860ee09",
    "index": 0,
    "_id": "5719e3e274100077317814b9"
  },
  {
    "secondaireSports": "Walking",
    "favoriteSports": "Surfing",
    "commentsFriends": [
      {
        "likes": 6,
        "comments": "Aute incididunt anim veniam est. Et in officia velit culpa. Nulla proident labore est duis anim. Est occaecat sit do est eu consectetur tempor voluptate aliqua laborum anim non. Dolore nulla laboris enim dolore est ea. Ea mollit fugiat laboris incididunt non qui tempor velit.",
        "picture": "http://placehold.it/32x32",
        "name": "Noemi Pitts",
        "id": 0
      }
    ],
    "longitude": "-131.81503",
    "latitude": "-52.271423",
    "registered": "Tuesday, July 14, 2015 5:04 PM",
    "address": "784 Nassau Avenue, Castleton, New Jersey, 8305",
    "houseAvailability": "2 nights minimum stay",
    "houseSpaceDescription": "Sit ipsum ex pariatur sint elit veniam magna eiusmod esse est veniam. Nostrud eiusmod amet aute dolore ipsum laborum ea laborum.",
    "housePrices": {
      "cancellation": "proident",
      "securityDeposit": "$2,069.47",
      "monthlyDiscount": "100%",
      "cleaningFee": "$2,163.74",
      "weeklyDiscount": "200%",
      "extraBabyBed": "$3,173.64 consectetur minim"
    },
    "houseAmenities": {
      "more": "Eiusmod amet laborum qui mollit.",
      "bbq": false,
      "essentials": true,
      "TV": true,
      "wifi": false,
      "kitchen": true
    },
    "houseSpace": {
      "houseRules": "Elit esse anim proident mollit consequat eiusmod in laboris consequat quis laboris labore. Esse veniam culpa laboris nulla ad in voluptate. Aliquip nulla laborum do do sint magna. Veniam velit eu laboris ea dolor labore sint. Tempor ipsum esse cupidatat irure ad dolore nostrud officia eiusmod consequat laboris ea non. Ex sunt sunt aute in aute enim veniam nisi cupidatat sit et. Veniam incididunt id eu do cillum ea nisi.",
      "checkOut": "11:00 AM",
      "checkIn": "2:00 PM",
      "propertyType": "et ea",
      "beds": 4,
      "bedrooms": 5,
      "bathrooms": 2,
      "accommodates": 7
    },
    "houseListing": {
      "valueForMoney": "5 stars",
      "location": "5 stars",
      "cleanness": "5 stars",
      "price": "$1,118.78",
      "country": "Montserrat",
      "state": "Virginia",
      "description": "Cillum culpa occaecat nostrud exercitation. Fugiat reprehenderit officia aliqua quis minim culpa. Do aliquip voluptate veniam elit ea consectetur deserunt ex voluptate in ea irure ea. Ea nostrud irure nulla ea enim est do velit commodo elit laborum.",
      "title": "Ut sint mollit esse esse exercitation magna Lorem consectetur anim adipisicing ipsum esse."
    },
    "name": {
      "last": "Johnston",
      "first": "Francesca"
    },
    "picture": "http://placehold.it/1900x400",
    "isActive": false,
    "guid": "82daa01c-871f-41f8-9137-61e6f39cf03d",
    "index": 1,
    "_id": "5719e3e26c16a821bec95e03"
  },
  {
    "secondaireSports": "Basketball",
    "favoriteSports": "Horse riding",
    "commentsFriends": [
      {
        "likes": 6,
        "comments": "Aute incididunt anim veniam est. Et in officia velit culpa. Nulla proident labore est duis anim. Est occaecat sit do est eu consectetur tempor voluptate aliqua laborum anim non. Dolore nulla laboris enim dolore est ea. Ea mollit fugiat laboris incididunt non qui tempor velit.",
        "picture": "http://placehold.it/32x32",
        "name": "Noemi Pitts",
        "id": 0
      }
    ],
    "longitude": "115.882084",
    "latitude": "-41.780367",
    "registered": "Thursday, April 16, 2015 12:32 AM",
    "address": "309 Sackett Street, Grimsley, Montana, 668",
    "houseAvailability": "2 nights minimum stay",
    "houseSpaceDescription": "Est aliquip duis nulla aliquip minim qui anim consequat aliqua magna est do labore mollit. Pariatur consectetur amet irure minim excepteur anim.",
    "housePrices": {
      "cancellation": "irure",
      "securityDeposit": "$2,417.82",
      "monthlyDiscount": "400%",
      "cleaningFee": "$2,784.79",
      "weeklyDiscount": "200%",
      "extraBabyBed": "$1,001.22 deserunt reprehenderit"
    },
    "houseAmenities": {
      "more": "Irure cillum proident consectetur velit consectetur esse sunt.",
      "bbq": true,
      "essentials": true,
      "TV": false,
      "wifi": true,
      "kitchen": false
    },
    "houseSpace": {
      "houseRules": "Eu duis nostrud duis est laboris velit laborum sunt. Qui est ipsum minim dolor aliquip deserunt irure dolor culpa sint anim. Et dolor ipsum sint enim consectetur occaecat magna reprehenderit. Elit ut Lorem quis incididunt consectetur reprehenderit proident id nisi officia magna et. Sit sint esse nulla proident commodo ea nisi sunt cupidatat cupidatat commodo labore.",
      "checkOut": "11:00 AM",
      "checkIn": "2:00 PM",
      "propertyType": "ad fugiat",
      "beds": 4,
      "bedrooms": 3,
      "bathrooms": 1,
      "accommodates": 7
    },
    "houseListing": {
      "valueForMoney": "5 stars",
      "location": "5 stars",
      "cleanness": "5 stars",
      "price": "$3,492.76",
      "country": "Macedonia",
      "state": "Idaho",
      "description": "Excepteur sint minim ad esse. Laboris cupidatat commodo veniam ipsum aute veniam consequat consequat in Lorem eiusmod culpa esse. Excepteur aute minim occaecat mollit est cillum elit reprehenderit. In ut consequat consectetur ipsum esse quis elit labore elit excepteur et quis voluptate. Veniam amet nulla eu duis sint Lorem amet enim reprehenderit dolor labore mollit.",
      "title": "Dolore cillum cillum irure ut dolore dolore sunt reprehenderit magna fugiat."
    },
    "name": {
      "last": "Mosley",
      "first": "Lawson"
    },
    "picture": "http://placehold.it/1900x400",
    "isActive": true,
    "guid": "16fa1bed-a1c1-4d29-aa74-c46f7d7b66e7",
    "index": 2,
    "_id": "5719e3e34e64c0ca56e008f9"
  },
  {
    "secondaireSports": "Jogging",
    "favoriteSports": "Biking",
    "commentsFriends": [
      {
        "likes": 6,
        "comments": "Aute incididunt anim veniam est. Et in officia velit culpa. Nulla proident labore est duis anim. Est occaecat sit do est eu consectetur tempor voluptate aliqua laborum anim non. Dolore nulla laboris enim dolore est ea. Ea mollit fugiat laboris incididunt non qui tempor velit.",
        "picture": "http://placehold.it/32x32",
        "name": "Noemi Pitts",
        "id": 0
      }
    ],
    "longitude": "7.432298",
    "latitude": "59.958096",
    "registered": "Sunday, November 29, 2015 2:33 PM",
    "address": "359 Furman Avenue, Dante, Louisiana, 9152",
    "houseAvailability": "2 nights minimum stay",
    "houseSpaceDescription": "Exercitation minim adipisicing anim eu ad anim sunt pariatur. Occaecat incididunt magna do ullamco aliquip sit dolore veniam nostrud.",
    "housePrices": {
      "cancellation": "ipsum",
      "securityDeposit": "$3,259.40",
      "monthlyDiscount": "400%",
      "cleaningFee": "$1,706.85",
      "weeklyDiscount": "100%",
      "extraBabyBed": "$1,879.20 voluptate deserunt"
    },
    "houseAmenities": {
      "more": "Duis laborum mollit reprehenderit officia dolor occaecat adipisicing esse nulla.",
      "bbq": false,
      "essentials": false,
      "TV": true,
      "wifi": false,
      "kitchen": true
    },
    "houseSpace": {
      "houseRules": "Sint nisi dolor eu commodo. Nostrud cupidatat aute nulla laborum. Cillum qui do id sunt exercitation cillum fugiat cillum sint est et. Nostrud excepteur ex esse consectetur veniam ut culpa veniam eiusmod duis irure Lorem laboris.",
      "checkOut": "11:00 AM",
      "checkIn": "2:00 PM",
      "propertyType": "et duis",
      "beds": 5,
      "bedrooms": 1,
      "bathrooms": 1,
      "accommodates": 1
    },
    "houseListing": {
      "valueForMoney": "5 stars",
      "location": "5 stars",
      "cleanness": "5 stars",
      "price": "$1,024.87",
      "country": "Ukraine",
      "state": "Minnesota",
      "description": "Tempor aute est minim exercitation dolore enim tempor do. Dolore adipisicing incididunt magna sit amet anim duis et aute aliqua. Qui culpa occaecat ad consectetur. Eu sint tempor in commodo pariatur pariatur. Eu ipsum commodo esse ullamco laboris incididunt magna non. Aliqua proident eiusmod quis eu ad dolor ea quis ea quis irure commodo nostrud esse. Deserunt qui duis consequat aliqua consequat sunt adipisicing.",
      "title": "Nostrud dolore sunt amet ullamco deserunt do occaecat."
    },
    "name": {
      "last": "Brennan",
      "first": "Mcleod"
    },
    "picture": "http://placehold.it/1900x400",
    "isActive": true,
    "guid": "04bb1267-87e1-451e-99c7-f21878ea2800",
    "index": 3,
    "_id": "5719e3e3a70d102d060de06b"
  },
  {
    "secondaireSports": "Paintball",
    "favoriteSports": "Hiking",
    "commentsFriends": [
      {
        "likes": 6,
        "comments": "Aute incididunt anim veniam est. Et in officia velit culpa. Nulla proident labore est duis anim. Est occaecat sit do est eu consectetur tempor voluptate aliqua laborum anim non. Dolore nulla laboris enim dolore est ea. Ea mollit fugiat laboris incididunt non qui tempor velit.",
        "picture": "http://placehold.it/32x32",
        "name": "Noemi Pitts",
        "id": 0
      }
    ],
    "longitude": "63.54418",
    "latitude": "-54.766965",
    "registered": "Wednesday, April 30, 2014 1:34 AM",
    "address": "768 Lexington Avenue, Bath, West Virginia, 383",
    "houseAvailability": "2 nights minimum stay",
    "houseSpaceDescription": "Ipsum est anim nisi est minim amet quis velit qui ipsum nostrud fugiat adipisicing enim. Veniam Lorem amet exercitation cupidatat anim eiusmod ex cupidatat do excepteur fugiat.",
    "housePrices": {
      "cancellation": "aliquip",
      "securityDeposit": "$3,753.44",
      "monthlyDiscount": "200%",
      "cleaningFee": "$3,096.02",
      "weeklyDiscount": "200%",
      "extraBabyBed": "$1,153.59 est dolore"
    },
    "houseAmenities": {
      "more": "Nulla magna exercitation commodo esse sint cillum quis reprehenderit elit nulla ullamco occaecat velit.",
      "bbq": true,
      "essentials": false,
      "TV": true,
      "wifi": false,
      "kitchen": true
    },
    "houseSpace": {
      "houseRules": "Ea duis officia enim consequat nisi. Culpa tempor aliquip aliqua eu consequat laboris mollit duis nulla tempor veniam. Nisi proident aliquip sit irure minim pariatur mollit proident sunt nulla aliquip minim veniam. Consequat magna officia proident nisi eiusmod pariatur incididunt velit exercitation veniam labore reprehenderit.",
      "checkOut": "11:00 AM",
      "checkIn": "2:00 PM",
      "propertyType": "laboris magna",
      "beds": 7,
      "bedrooms": 6,
      "bathrooms": 3,
      "accommodates": 9
    },
    "houseListing": {
      "valueForMoney": "5 stars",
      "location": "5 stars",
      "cleanness": "5 stars",
      "price": "$2,400.30",
      "country": "Norfolk Island",
      "state": "Pennsylvania",
      "description": "Est aliqua ad occaecat aliquip minim. Proident id velit cupidatat do laborum ex nulla Lorem voluptate veniam aliquip eiusmod ad. Elit irure fugiat commodo nostrud aute deserunt irure cillum ut nisi sunt nostrud adipisicing. Est duis ipsum amet proident ad veniam reprehenderit.",
      "title": "Quis eiusmod quis laborum laboris commodo."
    },
    "name": {
      "last": "Green",
      "first": "Richards"
    },
    "picture": "http://placehold.it/1900x400",
    "isActive": false,
    "guid": "b277e690-eba2-44da-b59a-12cf28cf5a2b",
    "index": 4,
    "_id": "5719e3e393ef13d81f8247e2"
  }
